resitor/ResourceMonitor.py
resitor/__init__.py
resitor/__main__.py
resitor-1.0.2.dist-info/METADATA
resitor-1.0.2.dist-info/WHEEL
resitor-1.0.2.dist-info/entry_points.txt
resitor-1.0.2.dist-info/top_level.txt
resitor-1.0.2.dist-info/RECORD
